PiStorms_scripts
