Metadata-Version: 1.0
Name: MSTest
Version: 1.92
Summary: mindsensors test
Home-page: http://www.mindsensors.com/
Author: mindsensors.com
Author-email: contact@mindsensors.com
License: UNKNOWN
Platform: UNKNOWN
